qtrade/__init__.py
qtrade/backtest/__init__.py
qtrade/backtest/backtest.py
qtrade/backtest/strategy.py
qtrade/core/__init__.py
qtrade/core/broker.py
qtrade/core/commission.py
qtrade/core/order.py
qtrade/core/position.py
qtrade/core/trade.py
qtrade/env/__init__.py
qtrade/env/actions.py
qtrade/env/environment.py
qtrade/env/observers.py
qtrade/env/rewards.py
qtrade/utils/__init__.py
qtrade/utils/evaluation.py
qtrade/utils/plot_bokeh.py
qtrade/utils/plotly.py
qtrade/utils/stats.py
qtrade_lib-0.1.3.dist-info/METADATA
qtrade_lib-0.1.3.dist-info/WHEEL
qtrade_lib-0.1.3.dist-info/entry_points.txt
qtrade_lib-0.1.3.dist-info/licenses/LICENSE
qtrade_lib-0.1.3.dist-info/RECORD
