Metadata-Version: 2.4
Name: qtrade-lib
Version: 0.1.3
Summary: A Python library for backtesting trading strategies and applying reinforcement learning to trading.
License: MIT
License-File: LICENSE
Keywords: trading,backtesting,reinforcement learning
Author: Guan Guan
Author-email: guanguan1114@gmail.com
Requires-Python: >=3.10,<4.0
Classifier: License :: OSI Approved :: MIT License
Classifier: Programming Language :: Python :: 3
Classifier: Programming Language :: Python :: 3.10
Classifier: Programming Language :: Python :: 3.11
Classifier: Programming Language :: Python :: 3.12
Classifier: Programming Language :: Python :: 3.13
Classifier: Programming Language :: Python :: 3.14
Requires-Dist: bokeh (>=3.3.0)
Requires-Dist: gymnasium (>=1.0.0)
Requires-Dist: matplotlib (>=3.3.0)
Requires-Dist: mplfinance (>=0.12.10b0)
Requires-Dist: numpy
Requires-Dist: pandas
Requires-Dist: scipy (>=1.6.0)
Requires-Dist: tqdm (>=4.0.0)
Project-URL: Homepage, https://github.com/gguan/qtrade
Project-URL: Repository, https://github.com/gguan/qtrade
